{
  "name": "Nord-Furs Silvester",
  "events": [
    {
      "id": "nord-furs-silvester-2025",
      "name": "Nord-Furs Silvester 2025",
      "url": "https://app.hi.events/event/3379/nord-furs-silvester",
      "startDate": "2025-12-30",
      "endDate": "2025-12-01",
      "venue": "DJH Jugendherberge Müden/Örtze",
      "address": "Wiesenweg 32, 29328 Faßberg, Deutschland",
      "locale": "de-DE",
      "latLng": [
        52.8673475,
        10.1192852
      ],
      "sources": [
        "fancons.com"
      ]
    }
  ]
}
