{
  "name": "Thaitails",
  "events": [
    {
      "id": "thaitails-2025",
      "name": "Thaitails 2025",
      "url": "https://thaitails.net",
      "startDate": "2025-03-22",
      "endDate": "2025-03-23",
      "venue": "โรงแรมแกรนด์ริชมอนด์",
      "address": "282 ถนน รัตนาธิเบศร์ บางกระสอ อำเภอเมืองนนทบุรี นนทบุรี 11000 ไทย",
      "locale": "th-TH",
      "translations": {
        "en": {
          "venue": "Grand Richmond Stylish Convention Hotel",
          "address": "282 Thanon Rattanathibet, Tambon Bang Kraso, Amphoe Mueang Nonthaburi, Chang Wat Nonthaburi 11000, Thailand"
        }
      },
      "latLng": [
        13.8615278,
        100.5068041
      ]
    }
  ]
}
